{
	"configurations" : 
	[
		{
			"directories" : 
			[
				{
					"build" : ".",
					"minimumCMakeVersion" : 
					{
						"string" : "3.1"
					},
					"projectIndex" : 0,
					"source" : ".",
					"targetIndexes" : 
					[
						0
					]
				}
			],
			"name" : "Debug",
			"projects" : 
			[
				{
					"directoryIndexes" : 
					[
						0
					],
					"name" : "salmon",
					"targetIndexes" : 
					[
						0
					]
				}
			],
			"targets" : 
			[
				{
					"directoryIndex" : 0,
					"id" : "salmon::@6890427a1f51a3e7e1df",
					"jsonFile" : "target-salmon-Debug-d1d30d6066df551f54e8.json",
					"name" : "salmon",
					"projectIndex" : 0
				}
			]
		}
	],
	"kind" : "codemodel",
	"paths" : 
	{
		"build" : "C:/Users/viven/OneDrive/Desktop/team9-jvalana-moving/out/build/x64-Debug",
		"source" : "C:/Users/viven/OneDrive/Desktop/team9-jvalana-moving"
	},
	"version" : 
	{
		"major" : 2,
		"minor" : 0
	}
}
